README.md
setup.cfg
setup.py
certbot_dns_acmedns/__init__.py
certbot_dns_acmedns/dns_acmedns.py
certbot_dns_acmedns/dns_acmedns_test.py
certbot_dns_acmedns.egg-info/PKG-INFO
certbot_dns_acmedns.egg-info/SOURCES.txt
certbot_dns_acmedns.egg-info/dependency_links.txt
certbot_dns_acmedns.egg-info/entry_points.txt
certbot_dns_acmedns.egg-info/requires.txt
certbot_dns_acmedns.egg-info/top_level.txt